plot_joblog.py
plot_joblog-1.0.1.dist-info/entry_points.txt
plot_joblog-1.0.1.dist-info/DESCRIPTION.rst
plot_joblog-1.0.1.dist-info/WHEEL
plot_joblog-1.0.1.dist-info/top_level.txt
plot_joblog-1.0.1.dist-info/metadata.json
plot_joblog-1.0.1.dist-info/RECORD
plot_joblog-1.0.1.dist-info/METADATA
