Metadata-Version: 2.0
Name: plot-joblog
Version: 1.0.1
Summary: Produce a time chart of the jobs ran by GNU parallel
Home-page: https://github.com/ziotom78/plot_joblog
Author: Maurizio Tomasi
Author-email: ziotom78@gmail.com
License: MIT
Keywords: plot cli gnuparallel
Platform: UNKNOWN
Requires-Dist: Click
